discrete_test.py
main_ea.py
mixed_test.py
multiprocess_comparison.py
pytorch_test.py
EA_multiproc/EA_mixed.py
EA_multiproc/EA_pool.py
EA_multiproc/Eval_multiproc.py
EA_multiproc/Mut_multiproc.py
EA_multiproc/Pop_multiproc.py
EA_multiproc/Rec_multiproc.py
EA_multiproc/Sel_multiproc.py
EA_multiproc/__init__.py
EA_sequential/Crossover.py
EA_sequential/EA.py
EA_sequential/Evaluation.py
EA_sequential/Mutation.py
EA_sequential/Population.py
EA_sequential/Recombination.py
EA_sequential/Selection.py
EA_sequential/__init__.py
EA_torch/EA_torch.py
EA_torch/Evaluation_torch.py
EA_torch/Mutation_torch.py
EA_torch/Population_torch.py
EA_torch/Recombination_torch.py
EA_torch/Selection_torch.py
EA_torch/__init__.py
EA_framework-2.2.3.dist-info/LICENSE
EA_framework-2.2.3.dist-info/METADATA
EA_framework-2.2.3.dist-info/WHEEL
EA_framework-2.2.3.dist-info/top_level.txt
EA_framework-2.2.3.dist-info/RECORD
