Metadata-Version: 2.1
Name: EA_framework
Version: 2.2.3
Summary: A framework for applying evolutionary algorithms to generic optimization problems.
Author-email: Dimitrios Ieronymakis <dimitris.ieronymakis@gmail.com>
License: Copyright 2022 Dimitrios Ieronymakis
Project-URL: Homepage, https://github.com/OhGreat/evolutionary_algorithms
Project-URL: Bug Tracker, https://github.com/OhGreat/evolutionary_algorithms/issues
Classifier: Programming Language :: Python :: 3
Classifier: License :: OSI Approved :: MIT License
Classifier: Operating System :: OS Independent
Requires-Python: >=3.7
License-File: LICENSE
